LICENSE
MANIFEST.in
README.md
dev_requirements.txt
requirements.txt
setup.cfg
setup.py
graphql/__init__.py
graphql/grammar.py
graphql/graphql.py
graphql_python.egg-info/PKG-INFO
graphql_python.egg-info/SOURCES.txt
graphql_python.egg-info/dependency_links.txt
graphql_python.egg-info/requires.txt
graphql_python.egg-info/top_level.txt